ez_setup.py
setup.py
ContactGrabber.egg-info/PKG-INFO
ContactGrabber.egg-info/SOURCES.txt
ContactGrabber.egg-info/dependency_links.txt
ContactGrabber.egg-info/top_level.txt
contactgrabber/__init__.py
contactgrabber/base.py
contactgrabber/gmail.py
contactgrabber/main.py
contactgrabber/rediff.py
contactgrabber/yahoo.py