Metadata-Version: 1.0
Name: ContactGrabber
Version: 0.1
Summary: Grabs contacts from GMail, Yahoo!, Rediff etc.
Home-page: UNKNOWN
Author: Ranjan
Author-email: ranjan.naik@gmail.com
License: UNKNOWN
Platform: UNKNOWN
